xn_reverser/__init__.py
xn_reverser/xn_reverser.py
xn_reverser/data/unicode_ascii_mappings.json
xn_reverser-1.0.0.dist-info/LICENSE-2.0.txt
xn_reverser-1.0.0.dist-info/METADATA
xn_reverser-1.0.0.dist-info/WHEEL
xn_reverser-1.0.0.dist-info/top_level.txt
xn_reverser-1.0.0.dist-info/RECORD
