Metadata-Version: 2.1
Name: xn-reverser
Version: 1.0.0
Summary: Enumerate possible ASCII text being spoofed by a particular IDN domain name
Home-page: https://github.com/xn-twist/xn-reverser
Author: wesinator
Author-email: 13hurdw@gmail.com
License: UNKNOWN
Platform: UNKNOWN
Classifier: Intended Audience :: Developers
Classifier: License :: OSI Approved :: Apache Software License
Classifier: Natural Language :: English
Classifier: Programming Language :: Python :: 3
Requires-Dist: idna
